dummy/__init__.py
dummy/dummy2mqtt.py
dummy/dummy_interface.py
entry/__init__.py
entry/entry2mqtt.py
entry/entry_interface.py
gateway/__init__.py
gateway/configuration.py
gateway/mqtt_client.py
gateway/mqtt_map.py
gateway/start_gateway.py
gateway/start_gateway_test.py
gateway/test_messages.py
mqtt_gateways-0.2.dist-info/METADATA
mqtt_gateways-0.2.dist-info/RECORD
mqtt_gateways-0.2.dist-info/WHEEL
mqtt_gateways-0.2.dist-info/entry_points.txt
mqtt_gateways-0.2.dist-info/top_level.txt
musiccast/__init__.py
musiccast/dev_1.py
musiccast/musiccast2mqtt.py
musiccast/musiccast_checks.py
musiccast/musiccast_comm.py
musiccast/musiccast_data.py
musiccast/musiccast_device.py
musiccast/musiccast_exceptions.py
musiccast/musiccast_input.py
musiccast/musiccast_interface.py
musiccast/musiccast_system.py
musiccast/musiccast_zone.py
musiccast/ssdpdiscovery.py
musiccast/test_connect.py
