Metadata-Version: 2.1
Name: mqtt-gateways
Version: 0.2
Summary: Framework for MQTT Gateways
Home-page: http://mqtt-gateways.readthedocs.io/en/latest/
Author: Pier Paolo Taddonio
Author-email: paolo.taddonio@empiluma.com
License: MIT
Keywords: mqtt gateway
Platform: UNKNOWN
Classifier: Development Status :: 3 - Alpha
Classifier: Intended Audience :: Developers
Classifier: Topic :: Software Development :: Build Tools
Classifier: License :: OSI Approved :: MIT License
Classifier: Programming Language :: Python :: 2
Classifier: Programming Language :: Python :: 2.7
Classifier: Programming Language :: Python :: 3
Classifier: Programming Language :: Python :: 3.4
Classifier: Programming Language :: Python :: 3.5
Classifier: Programming Language :: Python :: 3.6
Requires-Dist: paho-mqtt (>=1.3.1)
Requires-Dist: pySerial (>=3.4)
